weblodge/__main__.py
weblodge/_azure/__init__.py
weblodge/_azure/appservice.py
weblodge/_azure/cli.py
weblodge/_azure/entra.py
weblodge/_azure/exceptions.py
weblodge/_azure/interfaces.py
weblodge/_azure/keyvault.py
weblodge/_azure/log_level.py
weblodge/_azure/resource.py
weblodge/_azure/resource_group.py
weblodge/_azure/service.py
weblodge/_azure/sku.py
weblodge/_azure/web_app.py
weblodge/cli/__init__.py
weblodge/cli/args.py
weblodge/cli/main.py
weblodge/config/__init__.py
weblodge/config/item.py
weblodge/parameters/__init__.py
weblodge/parameters/parameters.py
weblodge/state/__init__.py
weblodge/state/state.py
weblodge/web_app/__init__.py
weblodge/web_app/_all.py
weblodge/web_app/build.py
weblodge/web_app/delete.py
weblodge/web_app/deploy.py
weblodge/web_app/exceptions.py
weblodge/web_app/github.py
weblodge/web_app/logs.py
weblodge/web_app/shared.py
weblodge/web_app/tiers.py
weblodge/web_app/utils.py
weblodge/web_app/web_app.py
weblodge-0.6.1.dist-info/entry_points.txt
weblodge-0.6.1.dist-info/LICENSE
weblodge-0.6.1.dist-info/METADATA
weblodge-0.6.1.dist-info/WHEEL
weblodge-0.6.1.dist-info/RECORD
