Metadata-Version: 2.1
Name: weblodge
Version: 0.6.1
Summary: A simple command line aiming to provide anyone with deployment and cloud management capabilities.
Home-page: https://github.com/florian-vuillemot/weblodge
Keywords: deployment,azure
Author: Vuillemot Florian
Author-email: vuillemot.florian@outlook.fr
Requires-Python: >=3.8,<3.12
Classifier: Programming Language :: Python :: 3
Classifier: Programming Language :: Python :: 3.8
Classifier: Programming Language :: Python :: 3.9
Classifier: Programming Language :: Python :: 3.10
Classifier: Programming Language :: Python :: 3.11
Requires-Dist: azure-cli (>=2.40.0)
Requires-Dist: python-dotenv (>=0.19.0)
Project-URL: Repository, https://github.com/florian-vuillemot/weblodge
